fase2/lpm_mult.vhd
--------------------------------------------------------------------------------
-- lpm_mult: modelo behavioral del multiplicador con signo IP de Altera
-- Para SINTESIS: sustituir por la IP lpm_mult generada en Quartus (catalogo IP)
-- Para SIMULACION: este modelo calcula dataa * datab como numeros con signo
-- Entradas:  dataa, datab (11 bits complemento a 2)
-- Salida:    result (22 bits complemento a 2, result = dataa * datab)
--------------------------------------------------------------------------------
library ieee;
use ieee.std_logic_1164.all;
use ieee.numeric_std.all;

entity lpm_mult is
    port(
        dataa  : in  std_logic_vector(10 downto 0);
        datab  : in  std_logic_vector(10 downto 0);
        result : out std_logic_vector(21 downto 0)
    );
end entity;

architecture behavioral of lpm_mult is
begin
    process(dataa, datab)
        variable a : signed(10 downto 0);
        variable b : signed(10 downto 0);
        variable r : signed(21 downto 0);
    begin
        a := signed(dataa);
        b := signed(datab);
        r := a * b;
        result <= std_logic_vector(r);
    end process;
end behavioral;

fase2/alu.vhd
--------------------------------------------------------------------------------
-- ALU: Unidad Aritmético-Lógica para la calculadora
-- Operaciones: suma, resta, multiplicación en complemento a 2
--
-- Entradas:
--   op1, op2 : 11 bits complemento a 2 (rango -999..+999)
--   op       : "00"=suma, "01"=resta, "10"=multiplicacion
-- Salidas:
--   res      : 20 bits, valor absoluto del resultado
--   res_sgn  : '1' si el resultado es negativo
--   overflow : siempre '0' (los operandos +-999 no pueden desbordar 20 bits)
--
-- La multiplicacion usa el componente lpm_mult (signed 11x11 -> 22 bits).
-- Para simulacion: incluir fase2/lpm_mult.vhd (modelo behavioral).
-- Para sintesis:   generar la IP lpm_mult desde el catalogo de Quartus.
--------------------------------------------------------------------------------
library ieee;
use ieee.std_logic_1164.all;
use ieee.std_logic_unsigned.all;

entity alu is
    port(
        op1      : in  std_logic_vector(10 downto 0);  -- complemento a 2
        op2      : in  std_logic_vector(10 downto 0);  -- complemento a 2
        op       : in  std_logic_vector(1 downto 0);   -- 00=+  01=-  10=*
        res      : out std_logic_vector(19 downto 0);  -- magnitud resultado
        res_sgn  : out std_logic;                      -- 0=positivo, 1=negativo
        overflow : out std_logic                       -- siempre '0' en esta version
    );
end entity;

architecture rtl of alu is

    -- Extension de signo a 12 bits para suma/resta
    signal op1_12    : std_logic_vector(11 downto 0);
    signal op2_12    : std_logic_vector(11 downto 0);
    signal sum_12    : std_logic_vector(11 downto 0);
    signal sub_12    : std_logic_vector(11 downto 0);

    -- Resultado del multiplicador (22 bits complemento a 2)
    signal mult_res  : std_logic_vector(21 downto 0);

    -- Complementos a 2 para extraer magnitud (sin variables)
    signal sum_neg  : std_logic_vector(11 downto 0);
    signal sub_neg  : std_logic_vector(11 downto 0);
    signal mul_neg  : std_logic_vector(21 downto 0);

    component lpm_mult is
        port(
            dataa  : in  std_logic_vector(10 downto 0);
            datab  : in  std_logic_vector(10 downto 0);
            result : out std_logic_vector(21 downto 0)
        );
    end component;

begin

    -- Extension de signo de 11 a 12 bits (replica el bit de signo)
    op1_12 <= op1(10) & op1;
    op2_12 <= op2(10) & op2;

    -- Suma y resta combinacionales (12 bits)
    sum_12 <= op1_12 + op2_12;
    sub_12 <= op1_12 - op2_12;

    -- Multiplicador con signo 11x11 -> 22 bits
    U_MULT: lpm_mult
        port map(
            dataa  => op1,
            datab  => op2,
            result => mult_res
        );

    overflow <= '0';

    -- Complementos a 2 para extraer magnitud (combinacional, sin variables)
    sum_neg <= (not sum_12) + 1;
    sub_neg <= (not sub_12) + 1;
    mul_neg <= (not mult_res) + 1;

    -- Magnitud del resultado segun operacion y signo
    res <= "00000000" & sum_neg      when op = "00" and sum_12(11)   = '1' else
           "00000000" & sum_12       when op = "00"                       else
           "00000000" & sub_neg      when op = "01" and sub_12(11)   = '1' else
           "00000000" & sub_12       when op = "01"                       else
           mul_neg(19 downto 0)      when op = "10" and mult_res(21) = '1' else
           mult_res(19 downto 0);

    -- Signo del resultado: '1' si negativo
    res_sgn <= '1' when (op = "00" and sum_12(11)   = '1') or
                        (op = "01" and sub_12(11)   = '1') or
                        (op = "10" and mult_res(21) = '1') else '0';

end rtl;

fase2/tb_alu.vhd
--------------------------------------------------------------------------------
-- tb_alu: banco de pruebas para la ALU de la calculadora
-- La ALU es combinacional: se cambian las entradas y se espera propagacion
--
-- Casos de prueba:
--   Suma:   100 + 200 = +300
--           (-100) + (-200) = -300
--           (-100) + 200 = +100
-- Resta:    300 - 100 = +200
--           100 - 300 = -200
-- Producto: 12 * 12 = +144
--           (-3) * 5 = -15
--           999 * 999 = +998001
--
-- Representacion complemento a 2 de 11 bits (precomputadas):
--   +100 = "00001100100"   -100 = "11110011100"
--   +200 = "00011001000"   -200 = "11100111000"
--   +300 = "00100101100"   -300 = "11011010100"
--   +12  = "00000001100"   -3   = "11111111101"
--   +5   = "00000000101"   +999 = "01111100111"
--------------------------------------------------------------------------------
library ieee;
use ieee.std_logic_1164.all;
use ieee.std_logic_unsigned.all;

entity tb_alu is
end entity;

architecture sim of tb_alu is

    signal op1     : std_logic_vector(10 downto 0);
    signal op2     : std_logic_vector(10 downto 0);
    signal op      : std_logic_vector(1 downto 0);
    signal res     : std_logic_vector(19 downto 0);
    signal res_sgn : std_logic;
    signal overflow: std_logic;

    -- Constantes para operandos en complemento a 2 (11 bits)
    constant C_P100  : std_logic_vector(10 downto 0) := "00001100100";  -- +100
    constant C_N100  : std_logic_vector(10 downto 0) := "11110011100";  -- -100
    constant C_P200  : std_logic_vector(10 downto 0) := "00011001000";  -- +200
    constant C_N200  : std_logic_vector(10 downto 0) := "11100111000";  -- -200
    constant C_P300  : std_logic_vector(10 downto 0) := "00100101100";  -- +300
    constant C_N300  : std_logic_vector(10 downto 0) := "11011010100";  -- -300
    constant C_P12   : std_logic_vector(10 downto 0) := "00000001100";  -- +12
    constant C_N3    : std_logic_vector(10 downto 0) := "11111111101";  -- -3
    constant C_P5    : std_logic_vector(10 downto 0) := "00000000101";  -- +5
    constant C_P999  : std_logic_vector(10 downto 0) := "01111100111";  -- +999

    -- Constantes de operacion
    constant OP_SUM : std_logic_vector(1 downto 0) := "00";
    constant OP_SUB : std_logic_vector(1 downto 0) := "01";
    constant OP_MUL : std_logic_vector(1 downto 0) := "10";

    procedure check(
        tag     : in string;
        got_mag : in std_logic_vector(19 downto 0);
        got_sgn : in std_logic;
        exp_mag : in integer;
        exp_sgn : in std_logic
    ) is
    begin
        assert got_sgn = exp_sgn
            report tag & ": signo incorrecto. Esperado " & std_logic'image(exp_sgn) &
                   " obtenido " & std_logic'image(got_sgn)
            severity error;
        assert got_mag = exp_mag
            report tag & ": magnitud incorrecta. Esperado " & integer'image(exp_mag) &
                   " obtenido " & integer'image(conv_integer(got_mag))
            severity error;
    end procedure;

begin

    -- Instancia del modulo bajo prueba
    U_ALU: entity work.alu(rtl)
        port map(
            op1      => op1,
            op2      => op2,
            op       => op,
            res      => res,
            res_sgn  => res_sgn,
            overflow => overflow
        );

    process
    begin
        -- Dejar tiempo de inicializacion
        op1 <= (others => '0');
        op2 <= (others => '0');
        op  <= OP_SUM;
        wait for 20 ns;

        -- ---- SUMA --------------------------------------------------------

        -- 100 + 200 = +300
        op1 <= C_P100; op2 <= C_P200; op <= OP_SUM; wait for 20 ns;
        check("100+200", res, res_sgn, 300, '0');

        -- (-100) + (-200) = -300
        op1 <= C_N100; op2 <= C_N200; op <= OP_SUM; wait for 20 ns;
        check("(-100)+(-200)", res, res_sgn, 300, '1');

        -- (-100) + 200 = +100
        op1 <= C_N100; op2 <= C_P200; op <= OP_SUM; wait for 20 ns;
        check("(-100)+200", res, res_sgn, 100, '0');

        -- ---- RESTA -------------------------------------------------------

        -- 300 - 100 = +200
        op1 <= C_P300; op2 <= C_P100; op <= OP_SUB; wait for 20 ns;
        check("300-100", res, res_sgn, 200, '0');

        -- 100 - 300 = -200
        op1 <= C_P100; op2 <= C_P300; op <= OP_SUB; wait for 20 ns;
        check("100-300", res, res_sgn, 200, '1');

        -- (-100) - 200 = -300
        op1 <= C_N100; op2 <= C_P200; op <= OP_SUB; wait for 20 ns;
        check("(-100)-200", res, res_sgn, 300, '1');

        -- ---- PRODUCTO ----------------------------------------------------

        -- 12 * 12 = +144
        op1 <= C_P12; op2 <= C_P12; op <= OP_MUL; wait for 20 ns;
        check("12*12", res, res_sgn, 144, '0');

        -- (-3) * 5 = -15
        op1 <= C_N3; op2 <= C_P5; op <= OP_MUL; wait for 20 ns;
        check("(-3)*5", res, res_sgn, 15, '1');

        -- 999 * 999 = 998001
        op1 <= C_P999; op2 <= C_P999; op <= OP_MUL; wait for 20 ns;
        check("999*999", res, res_sgn, 998001, '0');

        -- 0 * 999 = 0 (resultado cero es positivo)
        op1 <= (others => '0'); op2 <= C_P999; op <= OP_MUL; wait for 20 ns;
        check("0*999", res, res_sgn, 0, '0');

        report "tb_alu: todos los casos completados" severity note;
        assert false severity failure;
    end process;

end sim;

debug/tb_alu.vcd
$date
	Thu May 07 16:15:30 2026
$end
$version
	ModelSim Version 10.4d
$end
$timescale
	1ps
$end

$scope module tb_alu $end
$var wire 1 ! op1 [10] $end
$var wire 1 " op1 [9] $end
$var wire 1 # op1 [8] $end
$var wire 1 $ op1 [7] $end
$var wire 1 % op1 [6] $end
$var wire 1 & op1 [5] $end
$var wire 1 ' op1 [4] $end
$var wire 1 ( op1 [3] $end
$var wire 1 ) op1 [2] $end
$var wire 1 * op1 [1] $end
$var wire 1 + op1 [0] $end
$var wire 1 , op2 [10] $end
$var wire 1 - op2 [9] $end
$var wire 1 . op2 [8] $end
$var wire 1 / op2 [7] $end
$var wire 1 0 op2 [6] $end
$var wire 1 1 op2 [5] $end
$var wire 1 2 op2 [4] $end
$var wire 1 3 op2 [3] $end
$var wire 1 4 op2 [2] $end
$var wire 1 5 op2 [1] $end
$var wire 1 6 op2 [0] $end
$var wire 1 7 op [1] $end
$var wire 1 8 op [0] $end
$var wire 1 9 res [19] $end
$var wire 1 : res [18] $end
$var wire 1 ; res [17] $end
$var wire 1 < res [16] $end
$var wire 1 = res [15] $end
$var wire 1 > res [14] $end
$var wire 1 ? res [13] $end
$var wire 1 @ res [12] $end
$var wire 1 A res [11] $end
$var wire 1 B res [10] $end
$var wire 1 C res [9] $end
$var wire 1 D res [8] $end
$var wire 1 E res [7] $end
$var wire 1 F res [6] $end
$var wire 1 G res [5] $end
$var wire 1 H res [4] $end
$var wire 1 I res [3] $end
$var wire 1 J res [2] $end
$var wire 1 K res [1] $end
$var wire 1 L res [0] $end
$var wire 1 M res_sgn $end
$var wire 1 N overflow $end
$upscope $end
$enddefinitions $end
#0
$dumpvars
0M
0N
0!
0"
0#
0$
0%
0&
0'
0(
0)
0*
0+
0,
0-
0.
0/
00
01
02
03
04
05
06
07
08
09
0:
0;
0<
0=
0>
0?
0@
0A
0B
0C
0D
0E
0F
0G
0H
0I
0J
0K
0L
$end
#20000
13
10
1/
1)
1&
1%
1J
1I
1G
1D
#40000
12
11
00
0/
1.
1-
1,
1(
1'
0&
0%
1$
1#
1"
1!
1M
#60000
02
01
10
1/
0.
0-
0,
0M
0I
1F
0D
#80000
18
14
03
11
0/
0'
1&
0$
0"
0!
1M
1I
0F
1D
0M
0J
0G
1F
1E
0D
#100000
13
00
1.
0(
1%
0#
1M
#120000
04
01
10
1/
0.
1(
1'
0&
0%
1$
1#
1"
1!
1J
1G
0F
0E
1D
#140000
08
17
14
00
0/
0'
0$
0#
0"
0!
0J
0I
0D
1C
1B
1A
1>
0M
1H
0G
1E
0C
0B
0A
0>
#160000
16
03
1+
1'
1&
1%
1$
1#
1"
1!
1M
1L
1K
1J
1I
0H
0E
#180000
15
11
10
1/
1.
1-
1*
0(
0'
0!
0M
0K
0J
0I
1H
1G
1F
1C
1A
1@
1?
1<
1;
1:
19
#200000
0+
0*
0)
0&
0%
0$
0#
0"
0L
0H
0G
0F
0C
0A
0@
0?
0<
0;
0:
09
