fase1/bin_to_bcd.vhd
--------------------------------------------------------------------------------
-- Conversor Binario a BCD - Suma de pesos (método de Horner en BCD)
-- Para cada bit de MSB a LSB: acc = 2*acc + bit  (aritmética BCD)
-- Latencia: N_BITS ciclos
--------------------------------------------------------------------------------
library ieee;
use ieee.std_logic_1164.all;
use ieee.std_logic_unsigned.all;

entity bin_to_bcd is
    generic( N_BITS : natural := 20 );
    port(
        clk   : in  std_logic;
        nRst  : in  std_logic;
        start : in  std_logic;
        bin   : in  std_logic_vector(N_BITS-1 downto 0);
        done  : out std_logic;
        bcd   : out std_logic_vector(23 downto 0)
    );
end entity;

architecture rtl of bin_to_bcd is
    type state_type is (IDLE, CALC, FINISH);
    signal state     : state_type;
    signal acc_bcd   : std_logic_vector(23 downto 0);
    signal bin_reg   : std_logic_vector(N_BITS-1 downto 0);
    signal bits_left : integer range 0 to N_BITS;

    -- Cadena de carry BCD combinacional (un paso de Horner):
    --   acc_bcd_nuevo = 2*acc_bcd + bit_in  (en aritmetica BCD)
    -- Todo esto es logica combinacional pura; solo acc_bcd es un registro.
    signal bit_in          : std_logic;
    signal tmp0,tmp1,tmp2,tmp3,tmp4,tmp5 : std_logic_vector(4 downto 0);
    signal n0,n1,n2,n3,n4,n5             : std_logic_vector(3 downto 0);
    signal c1,c2,c3,c4,c5                : std_logic;

begin
    -- ---- Logica combinacional: cadena de carry BCD ----------------------
    -- bit_in: MSB del registro de desplazamiento (bit que entra en este ciclo)
    bit_in <= bin_reg(N_BITS-1);

    -- Digito 0 (unidades, bits 3:0)
    tmp0 <= ('0' & acc_bcd(3  downto  0)) + ('0' & acc_bcd(3  downto  0)) + ("0000" & bit_in);
    n0   <= tmp0(3 downto 0) + "0110" when tmp0 >= "01010" else tmp0(3 downto 0);
    c1   <= '1' when tmp0 >= "01010" else '0';

    -- Digito 1 (decenas, bits 7:4)
    tmp1 <= ('0' & acc_bcd(7  downto  4)) + ('0' & acc_bcd(7  downto  4)) + ("0000" & c1);
    n1   <= tmp1(3 downto 0) + "0110" when tmp1 >= "01010" else tmp1(3 downto 0);
    c2   <= '1' when tmp1 >= "01010" else '0';

    -- Digito 2 (centenas, bits 11:8)
    tmp2 <= ('0' & acc_bcd(11 downto  8)) + ('0' & acc_bcd(11 downto  8)) + ("0000" & c2);
    n2   <= tmp2(3 downto 0) + "0110" when tmp2 >= "01010" else tmp2(3 downto 0);
    c3   <= '1' when tmp2 >= "01010" else '0';

    -- Digito 3 (millares, bits 15:12)
    tmp3 <= ('0' & acc_bcd(15 downto 12)) + ('0' & acc_bcd(15 downto 12)) + ("0000" & c3);
    n3   <= tmp3(3 downto 0) + "0110" when tmp3 >= "01010" else tmp3(3 downto 0);
    c4   <= '1' when tmp3 >= "01010" else '0';

    -- Digito 4 (decenas de millar, bits 19:16)
    tmp4 <= ('0' & acc_bcd(19 downto 16)) + ('0' & acc_bcd(19 downto 16)) + ("0000" & c4);
    n4   <= tmp4(3 downto 0) + "0110" when tmp4 >= "01010" else tmp4(3 downto 0);
    c5   <= '1' when tmp4 >= "01010" else '0';

    -- Digito 5 (centenas de millar, bits 23:20)
    tmp5 <= ('0' & acc_bcd(23 downto 20)) + ('0' & acc_bcd(23 downto 20)) + ("0000" & c5);
    n5   <= tmp5(3 downto 0) + "0110" when tmp5 >= "01010" else tmp5(3 downto 0);

    -- ---- Proceso secuencial: solo registros, sin variables --------------
    process(clk, nRst)
    begin
        if nRst = '0' then
            state     <= IDLE;
            acc_bcd   <= (others => '0');
            bin_reg   <= (others => '0');
            bits_left <= 0;
            done      <= '0';

        elsif clk'event and clk = '1' then
            case state is

                when IDLE =>
                    if start = '1' then
                        done      <= '0';
                        acc_bcd   <= (others => '0');
                        bin_reg   <= bin;
                        bits_left <= N_BITS;
                        state     <= CALC;
                    end if;

                when CALC =>
                    if bits_left > 0 then
                        -- Registrar el nuevo valor BCD (calculado combinacionalmente)
                        acc_bcd   <= n5 & n4 & n3 & n2 & n1 & n0;
                        bin_reg   <= bin_reg(N_BITS-2 downto 0) & '0';
                        bits_left <= bits_left - 1;
                    else
                        state <= FINISH;
                    end if;

                when FINISH =>
                    done  <= '1';
                    state <= IDLE;

            end case;
        end if;
    end process;

    bcd <= acc_bcd;
end rtl;

tb_bin_to_bcd.vhd
--------------------------------------------------------------------------------
-- Testbench: bin_to_bcd
-- Casos simples y verificables. Ejecutar: run 2000 ns por conversion
-- En ModelSim 5.1: run 8000 ns cubre todas las pruebas
--------------------------------------------------------------------------------
library ieee;
use ieee.std_logic_1164.all;
use ieee.std_logic_unsigned.all;

entity tb_bin_to_bcd is
end entity;

architecture sim of tb_bin_to_bcd is
    signal clk   : std_logic := '0';
    signal nRst  : std_logic := '0';
    signal start : std_logic := '0';
    signal bin   : std_logic_vector(19 downto 0) := (others => '0');
    signal done  : std_logic := '0';
    signal bcd   : std_logic_vector(23 downto 0);

    constant clk_period : time := 20 ns;  -- 50 MHz
begin
    uut: entity work.bin_to_bcd
        generic map( N_BITS => 20 )
        port map(
            clk   => clk,
            nRst  => nRst,
            start => start,
            bin   => bin,
            done  => done,
            bcd   => bcd
        );

    -- Reloj 50 MHz
    clk_process: process
    begin
        clk <= '0'; wait for clk_period/2;
        clk <= '1'; wait for clk_period/2;
    end process;

    stim_proc: process

        -- Procedimiento auxiliar: lanza conversion y espera done = '1'
        -- Alinea con flanco de reloj antes de activar start para evitar
        -- condiciones de carrera entre start y el muestreo del estado
        procedure run_test(val : std_logic_vector(19 downto 0)) is
        begin
            -- Esperar flanco de subida de reloj para alinear
            wait until rising_edge(clk);
            bin   <= val;
            start <= '1';
            wait until rising_edge(clk);  -- done baja aqui (IDLE ve start)
            start <= '0';
            wait until done = '1';        -- esperar fin de conversion
            wait for clk_period * 2;      -- margen para ver resultado en waveform
        end procedure;

    begin
        -- Reset
        nRst <= '0';
        wait for 50 ns;
        nRst <= '1';
        wait for clk_period * 2;

        -- Caso 1: 0 -> BCD esperado 000_000 (0x000000)
        run_test("00000000000000000000");

        -- Caso 2: 1 -> BCD esperado 000_001 (0x000001)
        run_test("00000000000000000001");

        -- Caso 3: 9 -> BCD esperado 000_009 (0x000009)
        run_test("00000000000000001001");

        -- Caso 4: 10 -> BCD esperado 000_010 (0x000010)
        -- 10 en binario = 0000...001010
        run_test("00000000000000001010");

        -- Caso 5: 100 -> BCD esperado 000_100 (0x000100)
        -- 100 = 64+32+4 = 1100100
        run_test("00000000000001100100");

        -- Caso 6: 255 -> BCD esperado 000_255 (0x000255)
        -- 255 = 11111111
        run_test("00000000000011111111");

        -- Caso 7: 999 -> BCD esperado 000_999 (0x000999)
        -- 999 = 1111100111
        run_test("00000000001111100111");

        -- Caso 8: 1000 -> BCD esperado 001_000 (0x001000)
        -- 1000 = 1111101000
        run_test("00000000001111101000");

        -- Caso 9: 9999 -> BCD esperado 009_999 (0x009999)
        -- 9999 = 10011100001111
        run_test("00000010011100001111");

        -- Caso 10: 999999 -> BCD esperado 999_999 (0x999999)
        -- 999999 = 0xF423F = 11110100001000111111 b
        run_test("11110100001000111111");

        wait;
    end process;
end sim;

debug/tb_bin_to_bcd_bus.vcd
$date
	Wed May 06 10:20:23 2026
$end
$version
	ModelSim Version 10.4d
$end
$timescale
	1ps
$end

$scope module tb_bin_to_bcd $end
$var wire 1 ! clk $end
$var wire 1 " nRst $end
$var wire 1 # start $end
$var wire 20 Wbin bin $end
$var wire 1 8 done $end
$var wire 24 Wbcd bcd $end
$upscope $end
$enddefinitions $end
#0
$dumpvars
0!
0"
0#
08
b00000000000000000000 Wbin
b000000000000000000000000 Wbcd
$end
#10000
1!
#20000
0!
#30000
1!
#40000
0!
#50000
1!
1"
#60000
0!
#70000
1!
#80000
0!
#90000
1!
1#
#100000
0!
#110000
1!
0#
#120000
0!
#130000
1!
#140000
0!
#150000
1!
#160000
0!
#170000
1!
#180000
0!
#190000
1!
#200000
0!
#210000
1!
#220000
0!
#230000
1!
#240000
0!
#250000
1!
#260000
0!
#270000
1!
#280000
0!
#290000
1!
#300000
0!
#310000
1!
#320000
0!
#330000
1!
#340000
0!
#350000
1!
#360000
0!
#370000
1!
#380000
0!
#390000
1!
#400000
0!
#410000
1!
#420000
0!
#430000
1!
#440000
0!
#450000
1!
#460000
0!
#470000
1!
#480000
0!
#490000
1!
#500000
0!
#510000
1!
#520000
0!
#530000
1!
#540000
0!
#550000
1!
18
#560000
0!
#570000
1!
#580000
0!
#590000
1!
1#
b00000000000000000001 Wbin
#600000
0!
#610000
1!
0#
08
#620000
0!
#630000
1!
#640000
0!
#650000
1!
#660000
0!
#670000
1!
#680000
0!
#690000
1!
#700000
0!
#710000
1!
#720000
0!
#730000
1!
#740000
0!
#750000
1!
#760000
0!
#770000
1!
#780000
0!
#790000
1!
#800000
0!
#810000
1!
#820000
0!
#830000
1!
#840000
0!
#850000
1!
#860000
0!
#870000
1!
#880000
0!
#890000
1!
#900000
0!
#910000
1!
#920000
0!
#930000
1!
#940000
0!
#950000
1!
#960000
0!
#970000
1!
#980000
0!
#990000
1!
#1000000
0!
#1010000
1!
b000000000000000000000001 Wbcd
#1020000
0!
#1030000
1!
#1040000
0!
#1050000
1!
18
#1060000
0!
#1070000
1!
#1080000
0!
#1090000
1!
1#
b00000000000000001001 Wbin
#1100000
0!
#1110000
1!
0#
08
b000000000000000000000000 Wbcd
#1120000
0!
#1130000
1!
#1140000
0!
#1150000
1!
#1160000
0!
#1170000
1!
#1180000
0!
#1190000
1!
#1200000
0!
#1210000
1!
#1220000
0!
#1230000
1!
#1240000
0!
#1250000
1!
#1260000
0!
#1270000
1!
#1280000
0!
#1290000
1!
#1300000
0!
#1310000
1!
#1320000
0!
#1330000
1!
#1340000
0!
#1350000
1!
#1360000
0!
#1370000
1!
#1380000
0!
#1390000
1!
#1400000
0!
#1410000
1!
#1420000
0!
#1430000
1!
#1440000
0!
#1450000
1!
b000000000000000000000001 Wbcd
#1460000
0!
#1470000
1!
b000000000000000000000010 Wbcd
#1480000
0!
#1490000
1!
b000000000000000000000100 Wbcd
#1500000
0!
#1510000
1!
b000000000000000000001001 Wbcd
#1520000
0!
#1530000
1!
#1540000
0!
#1550000
1!
18
#1560000
0!
#1570000
1!
#1580000
0!
#1590000
1!
1#
b00000000000000001010 Wbin
#1600000
0!
#1610000
1!
0#
08
b000000000000000000000000 Wbcd
#1620000
0!
#1630000
1!
#1640000
0!
#1650000
1!
#1660000
0!
#1670000
1!
#1680000
0!
#1690000
1!
#1700000
0!
#1710000
1!
#1720000
0!
#1730000
1!
#1740000
0!
#1750000
1!
#1760000
0!
#1770000
1!
#1780000
0!
#1790000
1!
#1800000
0!
#1810000
1!
#1820000
0!
#1830000
1!
#1840000
0!
#1850000
1!
#1860000
0!
#1870000
1!
#1880000
0!
#1890000
1!
#1900000
0!
#1910000
1!
#1920000
0!
#1930000
1!
#1940000
0!
#1950000
1!
b000000000000000000000001 Wbcd
#1960000
0!
#1970000
1!
b000000000000000000000010 Wbcd
#1980000
0!
#1990000
1!
b000000000000000000000101 Wbcd
#2000000
0!
#2010000
1!
b000000000000000000010000 Wbcd
#2020000
0!
#2030000
1!
#2040000
0!
#2050000
1!
18
#2060000
0!
#2070000
1!
#2080000
0!
#2090000
1!
1#
b00000000000001100100 Wbin
#2100000
0!
#2110000
1!
0#
08
b000000000000000000000000 Wbcd
#2120000
0!
#2130000
1!
#2140000
0!
#2150000
1!
#2160000
0!
#2170000
1!
#2180000
0!
#2190000
1!
#2200000
0!
#2210000
1!
#2220000
0!
#2230000
1!
#2240000
0!
#2250000
1!
#2260000
0!
#2270000
1!
#2280000
0!
#2290000
1!
#2300000
0!
#2310000
1!
#2320000
0!
#2330000
1!
#2340000
0!
#2350000
1!
#2360000
0!
#2370000
1!
#2380000
0!
#2390000
1!
b000000000000000000000001 Wbcd
#2400000
0!
#2410000
1!
b000000000000000000000011 Wbcd
#2420000
0!
#2430000
1!
b000000000000000000000110 Wbcd
#2440000
0!
#2450000
1!
b000000000000000000010010 Wbcd
#2460000
0!
#2470000
1!
b000000000000000000100101 Wbcd
#2480000
0!
#2490000
1!
b000000000000000001010000 Wbcd
#2500000
0!
#2510000
1!
b000000000000000100000000 Wbcd
#2520000
0!
#2530000
1!
#2540000
0!
#2550000
1!
18
#2560000
0!
#2570000
1!
#2580000
0!
#2590000
1!
1#
b00000000000011111111 Wbin
#2600000
0!
#2610000
1!
0#
08
b000000000000000000000000 Wbcd
#2620000
0!
#2630000
1!
#2640000
0!
#2650000
1!
#2660000
0!
#2670000
1!
#2680000
0!
#2690000
1!
#2700000
0!
#2710000
1!
#2720000
0!
#2730000
1!
#2740000
0!
#2750000
1!
#2760000
0!
#2770000
1!
#2780000
0!
#2790000
1!
#2800000
0!
#2810000
1!
#2820000
0!
#2830000
1!
#2840000
0!
#2850000
1!
#2860000
0!
#2870000
1!
b000000000000000000000001 Wbcd
#2880000
0!
#2890000
1!
b000000000000000000000011 Wbcd
#2900000
0!
#2910000
1!
b000000000000000000000111 Wbcd
#2920000
0!
#2930000
1!
b000000000000000000010101 Wbcd
#2940000
0!
#2950000
1!
b000000000000000000110001 Wbcd
#2960000
0!
#2970000
1!
b000000000000000001100011 Wbcd
#2980000
0!
#2990000
1!
b000000000000000100100111 Wbcd
#3000000
0!
#3010000
1!
b000000000000001001010101 Wbcd
#3020000
0!
#3030000
1!
#3040000
0!
#3050000
1!
18
#3060000
0!
#3070000
1!
#3080000
0!
#3090000
1!
1#
b00000000001111100111 Wbin
#3100000
0!
#3110000
1!
0#
08
b000000000000000000000000 Wbcd
#3120000
0!
#3130000
1!
#3140000
0!
#3150000
1!
#3160000
0!
#3170000
1!
#3180000
0!
#3190000
1!
#3200000
0!
#3210000
1!
#3220000
0!
#3230000
1!
#3240000
0!
#3250000
1!
#3260000
0!
#3270000
1!
#3280000
0!
#3290000
1!
#3300000
0!
#3310000
1!
#3320000
0!
#3330000
1!
b000000000000000000000001 Wbcd
#3340000
0!
#3350000
1!
b000000000000000000000011 Wbcd
#3360000
0!
#3370000
1!
b000000000000000000000111 Wbcd
#3380000
0!
#3390000
1!
b000000000000000000010101 Wbcd
#3400000
0!
#3410000
1!
b000000000000000000110001 Wbcd
#3420000
0!
#3430000
1!
b000000000000000001100010 Wbcd
#3440000
0!
#3450000
1!
b000000000000000100100100 Wbcd
#3460000
0!
#3470000
1!
b000000000000001001001001 Wbcd
#3480000
0!
#3490000
1!
b000000000000010010011001 Wbcd
#3500000
0!
#3510000
1!
b000000000000100110011001 Wbcd
#3520000
0!
#3530000
1!
#3540000
0!
#3550000
1!
18
#3560000
0!
#3570000
1!
#3580000
0!
#3590000
1!
1#
b00000000001111101000 Wbin
#3600000
0!
#3610000
1!
0#
08
b000000000000000000000000 Wbcd
#3620000
0!
#3630000
1!
#3640000
0!
#3650000
1!
#3660000
0!
#3670000
1!
#3680000
0!
#3690000
1!
#3700000
0!
#3710000
1!
#3720000
0!
#3730000
1!
#3740000
0!
#3750000
1!
#3760000
0!
#3770000
1!
#3780000
0!
#3790000
1!
#3800000
0!
#3810000
1!
#3820000
0!
#3830000
1!
b000000000000000000000001 Wbcd
#3840000
0!
#3850000
1!
b000000000000000000000011 Wbcd
#3860000
0!
#3870000
1!
b000000000000000000000111 Wbcd
#3880000
0!
#3890000
1!
b000000000000000000010101 Wbcd
#3900000
0!
#3910000
1!
b000000000000000000110001 Wbcd
#3920000
0!
#3930000
1!
b000000000000000001100010 Wbcd
#3940000
0!
#3950000
1!
b000000000000000100100101 Wbcd
#3960000
0!
#3970000
1!
b000000000000001001010000 Wbcd
#3980000
0!
#3990000
1!
b000000000000010100000000 Wbcd
#4000000
0!
#4010000
1!
b000000000001000000000000 Wbcd
#4020000
0!
#4030000
1!
#4040000
0!
#4050000
1!
18
#4060000
0!
#4070000
1!
#4080000
0!
#4090000
1!
1#
b00000010011100001111 Wbin
#4100000
0!
#4110000
1!
0#
08
b000000000000000000000000 Wbcd
#4120000
0!
#4130000
1!
#4140000
0!
#4150000
1!
#4160000
0!
#4170000
1!
#4180000
0!
#4190000
1!
#4200000
0!
#4210000
1!
#4220000
0!
#4230000
1!
#4240000
0!
#4250000
1!
b000000000000000000000001 Wbcd
#4260000
0!
#4270000
1!
b000000000000000000000010 Wbcd
#4280000
0!
#4290000
1!
b000000000000000000000100 Wbcd
#4300000
0!
#4310000
1!
b000000000000000000001001 Wbcd
#4320000
0!
#4330000
1!
b000000000000000000011001 Wbcd
#4340000
0!
#4350000
1!
b000000000000000000111001 Wbcd
#4360000
0!
#4370000
1!
b000000000000000001111000 Wbcd
#4380000
0!
#4390000
1!
b000000000000000101010110 Wbcd
#4400000
0!
#4410000
1!
b000000000000001100010010 Wbcd
#4420000
0!
#4430000
1!
b000000000000011000100100 Wbcd
#4440000
0!
#4450000
1!
b000000000001001001001001 Wbcd
#4460000
0!
#4470000
1!
b000000000010010010011001 Wbcd
#4480000
0!
#4490000
1!
b000000000100100110011001 Wbcd
#4500000
0!
#4510000
1!
b000000001001100110011001 Wbcd
#4520000
0!
#4530000
1!
#4540000
0!
#4550000
1!
18
#4560000
0!
#4570000
1!
#4580000
0!
#4590000
1!
1#
b11110100001000111111 Wbin
#4600000
0!
#4610000
1!
0#
08
b000000000000000000000000 Wbcd
#4620000
0!
#4630000
1!
b000000000000000000000001 Wbcd
#4640000
0!
#4650000
1!
b000000000000000000000011 Wbcd
#4660000
0!
#4670000
1!
b000000000000000000000111 Wbcd
#4680000
0!
#4690000
1!
b000000000000000000010101 Wbcd
#4700000
0!
#4710000
1!
b000000000000000000110000 Wbcd
#4720000
0!
#4730000
1!
b000000000000000001100001 Wbcd
#4740000
0!
#4750000
1!
b000000000000000100100010 Wbcd
#4760000
0!
#4770000
1!
b000000000000001001000100 Wbcd
#4780000
0!
#4790000
1!
b000000000000010010001000 Wbcd
#4800000
0!
#4810000
1!
b000000000000100101110110 Wbcd
#4820000
0!
#4830000
1!
b000000000001100101010011 Wbcd
#4840000
0!
#4850000
1!
b000000000011100100000110 Wbcd
#4860000
0!
#4870000
1!
b000000000111100000010010 Wbcd
#4880000
0!
#4890000
1!
b000000010101011000100100 Wbcd
#4900000
0!
#4910000
1!
b000000110001001001001001 Wbcd
#4920000
0!
#4930000
1!
b000001100010010010011001 Wbcd
#4940000
0!
#4950000
1!
b000100100100100110011001 Wbcd
#4960000
0!
#4970000
1!
b001001001001100110011001 Wbcd
#4980000
0!
#4990000
1!
b010010011001100110011001 Wbcd
#5000000
0!
#5010000
1!
b100110011001100110011001 Wbcd
#5020000
0!
#5030000
1!
#5040000
0!
#5050000
1!
18
